{
    "type": {
        "收入": [
            "工资",
            "家里补助",
            "退款",
            "额外收入"
        ],
        "支出": [
            "游戏",
            "交通",
            "周边购买",
            "爱好消费",
            "饮食",
            "日用百货",
            "订阅服务",
            "住房相关",
            "零食饮料",
            "医药",
            "娱乐活动",
            "软件"
        ]
    },
    "date": {
        "year": 2023,
        "month": 11,
        "day": 20
    },
    "cost": 100,
    "account": [
        "借记卡",
        "信用卡"
    ],
    "description": "steam退款"
}